{
  "schema_version": 1,
  "netuid": 40,
  "name": "Chunking",
  "slug": "chunking",
  "status": "active",
  "categories": [
    "baseline-curated",
    "data-pipeline",
    "identity-reviewed",
    "official-website",
    "rag"
  ],
  "website_url": "https://subnet.chunking.com/",
  "source_repo": null,
  "notes": "Reviewed overlay for SN40 Chunking. Multiple public directories identify VectorChat as the team and subnet.chunking.com as the official website, but the website currently has an expired TLS certificate and the historical VectorChat/chunking_subnet repository returns 404.",
  "curation": {
    "level": "maintainer-reviewed",
    "review_state": "maintainer-reviewed",
    "reviewed_at": "2026-06-08T15:00:00.000Z",
    "verified_at": "2026-06-08T15:00:00.000Z",
    "source_count": 6,
    "gap_notes": [
      "subnet.chunking.com appears to be the official Chunking website, but its TLS certificate is currently expired and probe-derived status should be degraded.",
      "Previously discovered VectorChat/chunking_subnet source repository currently returns 404.",
      "No verified live source repository yet.",
      "No verified machine-readable OpenAPI/Swagger schema yet.",
      "No verified safe public subnet API endpoint yet.",
      "No verified SSE/event stream yet.",
      "No verified standalone static data artifact yet."
    ]
  },
  "surfaces": [
    {
      "id": "sn-40-chunking-website",
      "name": "Chunking website",
      "kind": "website",
      "url": "https://subnet.chunking.com/",
      "provider": "vectorchat",
      "auth_required": false,
      "authority": "provider-claimed",
      "public_safe": true,
      "source_urls": [
        "https://subnet.chunking.com/",
        "https://github.com/VectorChat/chunking_subnet"
      ],
      "probe": {
        "enabled": true,
        "method": "HEAD",
        "expect": "html",
        "timeout_ms": 10000
      },
      "rate_limit_notes": "Current simple probes fail TLS validation because the certificate is expired.",
      "notes": "Official-looking Chunking subnet website retained with degraded probe status until the TLS certificate is fixed."
    }
  ]
}
