{
  "contract_version": "2026-06-06.1",
  "generated_at": "1970-01-01T00:00:00.000Z",
  "name": "DSperse",
  "netuid": 2,
  "schema_version": 1,
  "slug": "sn-2",
  "summary": {
    "avg_latency_ms": 470,
    "degraded_count": 0,
    "failed_count": 0,
    "last_checked": "2026-06-06T09:20:18.377Z",
    "last_ok": "2026-06-06T09:20:18.377Z",
    "name": "DSperse",
    "netuid": 2,
    "ok_count": 5,
    "slug": "sn-2",
    "status": "ok",
    "surface_count": 5,
    "unknown_count": 0
  },
  "surfaces": [
    {
      "auth_required": false,
      "classification": "live",
      "content_type": "text/html; charset=utf-8",
      "error": null,
      "error_class": null,
      "kind": "dashboard",
      "last_checked": "2026-06-06T09:20:17.845Z",
      "last_ok": "2026-06-06T09:20:17.845Z",
      "latency_ms": 314,
      "method_tested": "HEAD",
      "netuid": 2,
      "private_redirect_blocked": false,
      "provider": "taomarketcap",
      "public_safe": true,
      "redirect_target": null,
      "status": "ok",
      "status_code": 200,
      "subnet_name": "DSperse",
      "subnet_slug": "sn-2",
      "surface_id": "sn-2-taomarketcap-dashboard",
      "uptime_sample_ratio": 1,
      "url": "https://taomarketcap.com/subnets/2",
      "verified_at": "2026-06-06T09:20:17.845Z"
    },
    {
      "auth_required": false,
      "classification": "live",
      "content_type": "text/html; charset=utf-8",
      "error": null,
      "error_class": null,
      "kind": "source-repo",
      "last_checked": "2026-06-06T09:20:18.349Z",
      "last_ok": "2026-06-06T09:20:18.349Z",
      "latency_ms": 752,
      "method_tested": "HEAD",
      "netuid": 2,
      "private_redirect_blocked": false,
      "provider": "taomarketcap",
      "public_safe": true,
      "redirect_target": null,
      "status": "ok",
      "status_code": 200,
      "subnet_name": "DSperse",
      "subnet_slug": "sn-2",
      "surface_id": "sn-2-taomarketcap-source-repo",
      "uptime_sample_ratio": 1,
      "url": "https://github.com/inference-labs-inc/subnet-2",
      "verified_at": "2026-06-06T09:20:18.349Z"
    },
    {
      "auth_required": false,
      "classification": "live",
      "content_type": "text/html; charset=utf-8",
      "error": null,
      "error_class": null,
      "kind": "website",
      "last_checked": "2026-06-06T09:20:17.744Z",
      "last_ok": "2026-06-06T09:20:17.744Z",
      "latency_ms": 120,
      "method_tested": "HEAD",
      "netuid": 2,
      "private_redirect_blocked": false,
      "provider": "taomarketcap",
      "public_safe": true,
      "redirect_target": null,
      "status": "ok",
      "status_code": 200,
      "subnet_name": "DSperse",
      "subnet_slug": "sn-2",
      "surface_id": "sn-2-taomarketcap-website",
      "uptime_sample_ratio": 1,
      "url": "https://subnet2.inferencelabs.com/",
      "verified_at": "2026-06-06T09:20:17.744Z"
    },
    {
      "auth_required": false,
      "classification": "live",
      "content_type": "text/html; charset=utf-8",
      "error": null,
      "error_class": null,
      "kind": "docs",
      "last_checked": "2026-06-06T09:20:18.377Z",
      "last_ok": "2026-06-06T09:20:18.377Z",
      "latency_ms": 641,
      "method_tested": "HEAD",
      "netuid": 2,
      "private_redirect_blocked": false,
      "provider": "taopedia-articles",
      "public_safe": true,
      "redirect_target": null,
      "status": "ok",
      "status_code": 200,
      "subnet_name": "DSperse",
      "subnet_slug": "sn-2",
      "surface_id": "sn-2-taopedia-article",
      "uptime_sample_ratio": 1,
      "url": "https://github.com/e35ventura/taopedia-articles/blob/main/content/pages/subnet_2/index.mdx",
      "verified_at": "2026-06-06T09:20:18.377Z"
    },
    {
      "auth_required": false,
      "classification": "live",
      "content_type": "text/html; charset=utf-8",
      "error": null,
      "error_class": null,
      "kind": "docs",
      "last_checked": "2026-06-06T09:20:18.268Z",
      "last_ok": "2026-06-06T09:20:18.268Z",
      "latency_ms": 524,
      "method_tested": "HEAD",
      "netuid": 2,
      "private_redirect_blocked": false,
      "provider": "tensorplex-subnet-docs",
      "public_safe": true,
      "redirect_target": null,
      "status": "ok",
      "status_code": 200,
      "subnet_name": "DSperse",
      "subnet_slug": "sn-2",
      "surface_id": "sn-2-tensorplex-docs",
      "uptime_sample_ratio": 1,
      "url": "https://github.com/tensorplex-labs/subnet-docs/tree/main/data/2",
      "verified_at": "2026-06-06T09:20:18.268Z"
    }
  ]
}
